{
  "Version": "2012-10-17",
  "Statement": [
    {
      "Effect": "Allow",
      "Action": [
        "ec2:DescribeInstances",
        "ec2:DescribeVolumes",
        "ec2:DescribeVpcs",
        "rds:DescribeDBInstances",
        "s3:ListAllMyBuckets",
        "s3:GetBucketLocation",
        "lambda:ListFunctions",
        "ecs:ListClusters",
        "ecs:ListServices",
        "ecs:DescribeServices",
        "iam:ListUsers",
        "iam:ListRoles"
      ],
      "Resource": "*"
    },
    {
      "Effect": "Allow",
      "Action": [
        "sns:Publish"
      ],
      "Resource": "*"
    }
  ]
}
